{
  "$schema": "https://json-structure.org/meta/core/v0/#",
  "$id": "https://raw.githubusercontent.com/api-evangelist/airflow/refs/heads/main/json-structure/airflow-dag-tag-response-structure.json",
  "name": "DagTagResponse",
  "description": "DAG Tag serializer for responses.",
  "type": "object",
  "properties": {
    "name": {
      "type": "string",
      "title": "Name"
    },
    "dag_id": {
      "type": "string",
      "title": "Dag Id"
    },
    "dag_display_name": {
      "type": "string",
      "title": "Dag Display Name"
    }
  },
  "required": [
    "name",
    "dag_id",
    "dag_display_name"
  ]
}