{
  "$schema": "https://json-schema.org/draft/2020-12/schema",
  "$id": "https://raw.githubusercontent.com/api-evangelist/airflow/refs/heads/main/json-schema/airflow-dag-version-response-schema.json",
  "title": "DagVersionResponse",
  "description": "Dag Version serializer for responses.",
  "type": "object",
  "properties": {
    "id": {
      "type": "string",
      "format": "uuid",
      "title": "Id"
    },
    "version_number": {
      "type": "integer",
      "title": "Version Number"
    },
    "dag_id": {
      "type": "string",
      "title": "Dag Id"
    },
    "bundle_name": {
      "anyOf": [
        {
          "type": "string"
        },
        {
          "type": "null"
        }
      ],
      "title": "Bundle Name"
    },
    "bundle_version": {
      "anyOf": [
        {
          "type": "string"
        },
        {
          "type": "null"
        }
      ],
      "title": "Bundle Version"
    },
    "created_at": {
      "type": "string",
      "format": "date-time",
      "title": "Created At"
    },
    "dag_display_name": {
      "type": "string",
      "title": "Dag Display Name"
    },
    "bundle_url": {
      "anyOf": [
        {
          "type": "string"
        },
        {
          "type": "null"
        }
      ],
      "title": "Bundle Url"
    }
  },
  "required": [
    "id",
    "version_number",
    "dag_id",
    "bundle_name",
    "bundle_version",
    "created_at",
    "dag_display_name",
    "bundle_url"
  ]
}